nifcloud/__init__.py
nifcloud/auth.py
nifcloud/configprovider.py
nifcloud/credentials.py
nifcloud/loaders.py
nifcloud/parsers.py
nifcloud/serialize.py
nifcloud/session.py
nifcloud/data/_retry.json
nifcloud/data/endpoints.json
nifcloud/data/sdk-default-configuration.json
nifcloud/data/computing/3.0/service-2.json
nifcloud/data/computing/3.0/waiters-2.json
nifcloud/data/devops/v1/service-2.json
nifcloud/data/devops-runner/v1/service-2.json
nifcloud/data/dns/2012-12-12N2013-12-16/service-2.json
nifcloud/data/ess/2010-12-01N2014-05-28/service-2.json
nifcloud/data/nas/N2016-02-24/service-2.json
nifcloud/data/nas/N2016-02-24/waiters-2.json
nifcloud/data/rdb/2013-05-15N2013-12-16/service-2.json
nifcloud/data/rdb/2013-05-15N2013-12-16/waiters-2.json
nifcloud/data/service-activity/2020-11-25/service-2.json
nifcloud/data/storage/2006-03-01/service-2.json
nifcloud/docs/__init__.py
nifcloud-1.17.0.dist-info/licenses/LICENSE.txt
nifcloud-1.17.0.dist-info/METADATA
nifcloud-1.17.0.dist-info/WHEEL
nifcloud-1.17.0.dist-info/top_level.txt
nifcloud-1.17.0.dist-info/RECORD
